<?xml version ="1.0" encoding = "UTF-8"?>
 <tests xmlns:xsi="http://www.w3.org/2001/XMLSchema-instance"
   xsi:noNamespaceSchemaLocation="/usr/bin/jtestcase-2.2.0/config/jtestcase.xsd">
     <class name="SampleTestTest">
       <!-- global params -->
         <params>         </params>
        <method name="testMain" test-case="1">
             <params>
               <param name="var1" type="java.lang.String[]">NULL</param>
             </params>
             <asserts>
                <assertgroup name="testResult">
                <assert name="testResult1" type="void" action="EQUALS">null</assert>
                </assertgroup>
             </asserts>
             <exception>java.lang.NullPointerException</exception>
        </method>

     </class>

 </tests>
